LICENSE.txt
MANIFEST
reload.sh
setup.cfg
setup.py
upload.sh
.idea/.gitignore
.idea/misc.xml
.idea/modules.xml
.idea/qwant.iml
.idea/vcs.xml
.idea/inspectionProfiles/profiles_settings.xml
__pycache__/test.cpython-37.pyc
qwant/README.md
qwant/__init__.py
qwant/lib.py
qwant.egg-info/PKG-INFO
qwant.egg-info/SOURCES.txt
qwant.egg-info/dependency_links.txt
qwant.egg-info/requires.txt
qwant.egg-info/top_level.txt
qwant/__pycache__/__init__.cpython-37.pyc
qwant/__pycache__/google.cpython-37.pyc
qwant/__pycache__/lib.cpython-37.pyc
qwant/__pycache__/predict.cpython-37.pyc
qwant/__pycache__/tf_idf.cpython-37.pyc